AUTHORS.rst
CONTRIBUTING.rst
HISTORY.rst
LICENSE
MANIFEST.in
README.rst
setup.cfg
setup.py
docs/Makefile
docs/authors.rst
docs/conf.py
docs/contributing.rst
docs/history.rst
docs/index.rst
docs/installation.rst
docs/make.bat
docs/modules.rst
docs/pyliveleak.rst
docs/readme.rst
docs/usage.rst
docs/_build/html/_static/ajax-loader.gif
docs/_build/html/_static/comment-bright.png
docs/_build/html/_static/comment-close.png
docs/_build/html/_static/comment.png
docs/_build/html/_static/down-pressed.png
docs/_build/html/_static/down.png
docs/_build/html/_static/file.png
docs/_build/html/_static/minus.png
docs/_build/html/_static/plus.png
docs/_build/html/_static/up-pressed.png
docs/_build/html/_static/up.png
pyliveleak/VERSION
pyliveleak/__init__.py
pyliveleak/categories.yml
pyliveleak/cli.py
pyliveleak/pyliveleak.py
pyliveleak.egg-info/PKG-INFO
pyliveleak.egg-info/SOURCES.txt
pyliveleak.egg-info/dependency_links.txt
pyliveleak.egg-info/entry_points.txt
pyliveleak.egg-info/not-zip-safe
pyliveleak.egg-info/requires.txt
pyliveleak.egg-info/top_level.txt
tests/__init__.py
tests/test_pyliveleak.py
tests/test-data/add_item.html
tests/test-data/add_item.json
tests/test-data/file.html
tests/test-data/foreman_cif.mp4
tests/test-data/index.html
tests/test-data/llbucs.html