Metadata-Version: 1.1
Name: pyliveleak
Version: 0.1.2
Summary: Uploads videos to liveleak.com
Home-page: https://github.com/mpenkov/pyliveleak
Author: Michael Penkov
Author-email: misha.penkov@gmail.com
License: MIT license
Download-URL: https://github.com/mpenkov/pyliveleak/archive/0.1.1.tar.gz
Keywords: pyliveleak,liveleak
Platform: UNKNOWN
Classifier: Development Status :: 2 - Pre-Alpha
Classifier: Intended Audience :: Developers
Classifier: License :: OSI Approved :: MIT License
Classifier: Natural Language :: English
Classifier: Programming Language :: Python :: 2
Classifier: Programming Language :: Python :: 2.6
Classifier: Programming Language :: Python :: 2.7
Classifier: Programming Language :: Python :: 3
Classifier: Programming Language :: Python :: 3.3
Classifier: Programming Language :: Python :: 3.4
Classifier: Programming Language :: Python :: 3.5
